{
  "resourceType": "Bundle",
  "id": "0",
  "type": "searchset",
  "total": 61730,
  "link": [ {
    "relation": "self",
    "url": "/v1/fhir/Organization?_count=2"
  }, {
    "relation": "next",
    "url": "/v1/fhir/Organization?_count=2&_getpagesoffset=2"
  } ],
  "entry": [ {
    "fullUrl": "/v1/fhir/Organization/organization-8451352933505760",
    "resource": {
      "resourceType": "Organization",
      "id": "organization-8451352933505760",
      "meta": {
        "versionId": "1.0",
        "lastUpdated": "2026-07-11T02:49:26.000+00:00",
        "profile": [ "http://hl7.org/fhir/us/davinci-pdex-plan-net/StructureDefinition/plannet-Organization" ]
      },
      "identifier": [ {
        "use": "official",
        "type": {
          "coding": [ {
            "code": "provider_id",
            "display": "Healthsparq Provider ID"
          } ]
        },
        "value": "8451352933505760"
      }, {
        "use": "official",
        "type": {
          "coding": [ {
            "code": "source_provider_key",
            "display": "Source Provider key"
          } ]
        },
        "value": "C10054871001"
      } ],
      "active": true,
      "type": [ {
        "coding": [ {
          "code": "fac",
          "display": "Facility"
        } ]
      } ],
      "name": "CVS Pharmacy",
      "telecom": [ {
        "system": "phone",
        "value": "6304065904",
        "use": "work"
      } ],
      "address": [ {
        "use": "work",
        "type": "physical",
        "text": "115 N Randall Rd Address(address1=115 N Randall Rd, address2=null, city=Batavia, state=IL, zip=60510, postalSubCode=null, county=Kane, country=US, point=Point(latitude=41.852356, longitude=-88.34291), distance=0.0)",
        "line": [ "115 N Randall Rd" ],
        "city": "Batavia",
        "district": "Kane",
        "state": "IL",
        "postalCode": "60510",
        "country": "US"
      } ],
      "partOf": {
        "extension": [ {
          "url": "http://hl7.org/fhir/StructureDefinition/data-absent-reason",
          "valueCode": "unknown"
        } ]
      },
      "endpoint": [ {
        "extension": [ {
          "url": "http://hl7.org/fhir/StructureDefinition/data-absent-reason",
          "valueCode": "unknown"
        } ]
      } ]
    }
  }, {
    "fullUrl": "/v1/fhir/Organization/organization-2360066239172039",
    "resource": {
      "resourceType": "Organization",
      "id": "organization-2360066239172039",
      "meta": {
        "versionId": "1.0",
        "lastUpdated": "2026-07-11T02:49:26.000+00:00",
        "profile": [ "http://hl7.org/fhir/us/davinci-pdex-plan-net/StructureDefinition/plannet-Organization" ]
      },
      "identifier": [ {
        "use": "official",
        "type": {
          "coding": [ {
            "code": "provider_id",
            "display": "Healthsparq Provider ID"
          } ]
        },
        "value": "2360066239172039"
      }, {
        "use": "official",
        "type": {
          "coding": [ {
            "code": "source_provider_key",
            "display": "Source Provider key"
          } ]
        },
        "value": "600212410001"
      } ],
      "active": true,
      "type": [ {
        "coding": [ {
          "code": "prvgrp",
          "display": "Provider Group"
        } ]
      } ],
      "name": "Strong Eye Care",
      "telecom": [ {
        "system": "phone",
        "value": "5852733937",
        "use": "work"
      } ],
      "address": [ {
        "use": "work",
        "type": "physical",
        "text": "170 Lac De Ville Blvd Address(address1=170 Lac De Ville Blvd, address2=null, city=Rochester, state=NY, zip=14618, postalSubCode=null, county=Monroe, country=US, point=Point(latitude=43.1252, longitude=-77.58711), distance=0.0)",
        "line": [ "170 Lac De Ville Blvd" ],
        "city": "Rochester",
        "district": "Monroe",
        "state": "NY",
        "postalCode": "14618",
        "country": "US"
      } ],
      "partOf": {
        "extension": [ {
          "url": "http://hl7.org/fhir/StructureDefinition/data-absent-reason",
          "valueCode": "unknown"
        } ]
      },
      "endpoint": [ {
        "extension": [ {
          "url": "http://hl7.org/fhir/StructureDefinition/data-absent-reason",
          "valueCode": "unknown"
        } ]
      } ]
    }
  } ]
}